{"types":["/iotschema/Property","/iotschema/acceptsInputData"],"children":[{"types":["/iotschema/TransitionTimeData"],"reader":"*","name":"expectedReturnType","description":"","restrictions":[],"writer":"*","metaInformation":{},"tags":[]}],"reader":"*","name":"acceptsTransitionTimeData","description":"'A property that relates an Interaction Pattern with its input ransitionTimeData.'","restrictions":[],"writer":"*","metaInformation":{"TYPE":"Property"},"tags":["Pattern","AcceptsInputData","Input","Interaction","Accepts","Time","Data","Transition","Property","AcceptsTransitionTimeData","InteractionPattern"]}