{"types":["/iotschema/Property","/iotschema/providesInteractionPattern"],"children":[{"types":["/iotschema/ApparentPowerA"],"reader":"*","name":"expectedReturnType","description":"","restrictions":[],"writer":"*","metaInformation":{},"tags":[]}],"reader":"*","name":"apparentPowera","description":"'A property that relates a capability with its ApparentPowerA interaction pattern.'","restrictions":[],"writer":"*","metaInformation":{"TYPE":"Property"},"tags":["ApparentPowera","Pattern","Provides","Interaction","Powera","ProvidesInteractionPattern","Property","Apparent","InteractionPattern"]}