{"types":["/iotschema/Property","/iotschema/providesInteractionPattern"],"children":[{"types":["/iotschema/MotionType"],"reader":"*","name":"expectedReturnType","description":"","restrictions":[],"writer":"*","metaInformation":{},"tags":[]}],"reader":"*","name":"motionType","description":"'A property that relates a capability with its MotionType interaction pattern.'","restrictions":[],"writer":"*","metaInformation":{"TYPE":"Property"},"tags":["Pattern","Provides","Interaction","MotionType","ProvidesInteractionPattern","Property","Type","Motion","InteractionPattern"]}