{"types":["/iotschema/Property","/iotschema/providesInteractionPattern"],"children":[{"types":["/iotschema/OverflowStatus"],"reader":"*","name":"expectedReturnType","description":"","restrictions":[],"writer":"*","metaInformation":{},"tags":[]}],"reader":"*","name":"overflowStatus","description":"'A property that relates a capability with its OverflowStatus interaction pattern.'","restrictions":[],"writer":"*","metaInformation":{"TYPE":"Property"},"tags":["Pattern","Provides","Status","Interaction","ProvidesInteractionPattern","OverflowStatus","Overflow","Property","InteractionPattern"]}