{"types":["/iotschema/Property"],"children":[{"types":["/iotschema/InteractionPattern"],"reader":"*","name":"expectedReturnType","description":"","restrictions":[],"writer":"*","metaInformation":{},"tags":[]}],"reader":"*","name":"providesInteractionPattern","description":"'A property that relates a capability with its interaction patterns.'","restrictions":[],"writer":"*","metaInformation":{"TYPE":"Property"},"tags":["Provides","Pattern","Interaction","ProvidesInteractionPattern","Property","InteractionPattern"]}